docrepotek/__init__.py
docrepotek/templates/__init__.py
docrepotek/templates/bug_report.py
docrepotek/templates/colors.py
docrepotek/templates/conduct.py
docrepotek/templates/contrib.py
docrepotek/templates/feature_requests.py
docrepotek/templates/funding.py
docrepotek/templates/gitattributes.py
docrepotek/templates/gitignore.py
docrepotek/templates/issues.py
docrepotek/templates/licences.py
docrepotek/templates/pull_requests.py
docrepotek/templates/readme.py
docrepotek/templates/workflows.py
templates/__init__.py
templates/bug_report.py
templates/conduct.py
templates/contrib.py
templates/feature_requests.py
templates/funding.py
templates/gitignore.py
templates/issues.py
templates/licences.py
templates/pull_requests.py
templates/readme.py
templates/workflows.py
initigitdoc-0.3.7.dist-info/LICENSE
initigitdoc-0.3.7.dist-info/METADATA
initigitdoc-0.3.7.dist-info/WHEEL
initigitdoc-0.3.7.dist-info/top_level.txt
initigitdoc-0.3.7.dist-info/RECORD
